.gitignore
README.md
setup.py
SpikesStoresAndUtils.egg-info/PKG-INFO
SpikesStoresAndUtils.egg-info/SOURCES.txt
SpikesStoresAndUtils.egg-info/dependency_links.txt
SpikesStoresAndUtils.egg-info/top_level.txt
src/stores/config.ini
src/stores/streamer_store.py
src/stores/twitch_store.py
src/utils/utils.py