Metadata-Version: 2.1
Name: SpikesStoresAndUtils
Version: 0.0.7
Summary: various tools used for the Spikes algorithms
Home-page: UNKNOWN
Author: Michael Rubinfeld
License: UNKNOWN
Platform: UNKNOWN
